CONTRIBUTING.md
LICENSE.md
MANIFEST.in
README.md
ddt2.py
setup.cfg
setup.py
ddt2.egg-info/PKG-INFO
ddt2.egg-info/SOURCES.txt
ddt2.egg-info/dependency_links.txt
ddt2.egg-info/top_level.txt
test/__init__.py
test/mycode.py
test/test_example.py
test/test_functional.py
test/data/test_custom_yaml_loader.yaml
test/data/test_data_dict.json
test/data/test_data_dict.yaml
test/data/test_data_dict_dict.json
test/data/test_data_dict_dict.yaml
test/data/test_data_list.json
test/data/test_data_list.yaml
test/data/test_functional_custom_tags.yaml